prometheus_pusher/__init__.py
prometheus_pusher/helper.py
prometheus_pusher/version.py
tests/__init__.py
tests/conftest.py
tests/test_helper.py
prometheus_pusher-0.1.0.dist-info/LICENSE
prometheus_pusher-0.1.0.dist-info/METADATA
prometheus_pusher-0.1.0.dist-info/WHEEL
prometheus_pusher-0.1.0.dist-info/top_level.txt
prometheus_pusher-0.1.0.dist-info/RECORD
